lss/__init__.py
lss/__main__.py
lss/color.py
lss/color_scheme.py
lss/constants.py
lss/file.py
lss/icons.py
lss-1.0.0.dist-info/LICENSE
lss-1.0.0.dist-info/METADATA
lss-1.0.0.dist-info/WHEEL
lss-1.0.0.dist-info/entry_points.txt
lss-1.0.0.dist-info/top_level.txt
lss-1.0.0.dist-info/RECORD
