Metadata-Version: 2.1
Name: lss
Version: 1.0.0
Summary: Cross-platform ls command
Home-page: https://github.com/operatios/lss
Author: operatios
License: UNKNOWN
Platform: UNKNOWN
Classifier: Development Status :: 5 - Production/Stable
Classifier: Environment :: Console
Classifier: License :: OSI Approved :: MIT License
Classifier: Programming Language :: Python :: 3.8
